easyliftover/__init__.py
easyliftover/fetch_sources.py
easyliftover/genomes.py
easyliftover/lifters/__init__.py
easyliftover/lifters/abstract.py
easyliftover/lifters/bed.py
easyliftover/lifters/bedgraph.py
easyliftover/lifters/bigwig.py
easyliftover/lifters/gff.py
easyliftover/lifters/pyliftover/.git
easyliftover/lifters/pyliftover/.gitignore
easyliftover/lifters/pyliftover/.travis.yml
easyliftover/lifters/pyliftover/CHANGELOG.txt
easyliftover/lifters/pyliftover/LICENSE
easyliftover/lifters/pyliftover/MANIFEST.in
easyliftover/lifters/pyliftover/README.rst
easyliftover/lifters/pyliftover/pyliftover/__init__.py
easyliftover/lifters/pyliftover/pyliftover/chainfile.py
easyliftover/lifters/pyliftover/pyliftover/intervaltree.py
easyliftover/lifters/pyliftover/pyliftover/liftover.py
easyliftover/lifters/pyliftover/setup.cfg
easyliftover/lifters/pyliftover/setup.py
easyliftover/lifters/pyliftover/tests/__init__.py
easyliftover/lifters/pyliftover/tests/chainfile_test.py
easyliftover/lifters/pyliftover/tests/data/README.txt
easyliftover/lifters/pyliftover/tests/data/hg17ToHg18.over.chain.gz
easyliftover/lifters/pyliftover/tests/data/hg17ToHg18.testpoints.txt.gz
easyliftover/lifters/pyliftover/tests/data/hg38ToHg19.over.chain.gz
easyliftover/lifters/pyliftover/tests/data/hg38ToHg19.testinput.txt
easyliftover/lifters/pyliftover/tests/data/hg38ToHg19.testoutput.txt
easyliftover/lifters/pyliftover/tests/data/mds42.to.mg1655.liftOver
easyliftover/lifters/pyliftover/tests/intervaltree_test.py
easyliftover/lifters/pyliftover/tests/liftover_test.py
easyliftover/lifters/pyliftover/tests/open_liftover_chain_file_test.py
easyliftover/lifters/vcf.py
easyliftover/lifters/wig.py
easyliftover/liftover.py
easyliftover/sources.json
easyliftover/sources.py
easyliftover/targets.py
easyliftover/types.json
easyliftover/types.py
easyliftover-0.0.17.dist-info/LICENSE
easyliftover-0.0.17.dist-info/METADATA
easyliftover-0.0.17.dist-info/WHEEL
easyliftover-0.0.17.dist-info/RECORD
