Metadata-Version: 2.1
Name: easyliftover
Version: 0.0.17
Summary: A python package for lifting over biological files
Home-page: https://github.com/biomedbigdata/easyLiftover
License: GPL3
Author: Nico Trummer
Author-email: nictru32@gmail.com
Requires-Python: >=3.9
Classifier: License :: Other/Proprietary License
Classifier: Programming Language :: Python :: 3
Classifier: Programming Language :: Python :: 3.9
Classifier: Programming Language :: Python :: 3.10
Classifier: Programming Language :: Python :: 3.11
Classifier: Programming Language :: Python :: 3.12
Provides-Extra: bigwig
Requires-Dist: beautifulsoup4 (>=4.9.3,<5.0.0)
Requires-Dist: numpy (>=1.25.2,<2.0.0) ; extra == "bigwig"
Requires-Dist: pybigwig (>=0.3.22,<0.4.0) ; extra == "bigwig"
Requires-Dist: requests (>=2.26.0,<3.0.0)
Project-URL: Repository, https://github.com/biomedbigdata/easyLiftover
